{
    "pools": [
        {
            "rolls": 1,
            "entries": [
                {
                    "type": "minecraft:item",
                    "name": "minecraft:emerald_block",
                    "functions": [
                        {
                            "function": "minecraft:set_name",
                            "entity": "this",
                            "name": {
                                "translate": "death_effects",
                                "italic": false,
                                "color": "#79ff2b"
                            }
                        },
                        {
                            "function": "minecraft:set_lore",
                            "mode": "replace_all",
                            "entity": "this",
                            "lore": [
                                {
                                    "translate": "death_effects.lore",
                                    "italic": false,
                                    "color": "white"
                                }
                            ]
                        }
                    ]
                }
            ]
        }
    ]
}